CHANGELOG.txt
LICENSE.txt
MANIFEST.in
README.txt
ez_setup.py
setup.cfg
setup.py
DreamweaverTemplate.egg-info/PKG-INFO
DreamweaverTemplate.egg-info/SOURCES.txt
DreamweaverTemplate.egg-info/dependency_links.txt
DreamweaverTemplate.egg-info/entry_points.txt
DreamweaverTemplate.egg-info/not-zip-safe
DreamweaverTemplate.egg-info/requires.txt
DreamweaverTemplate.egg-info/top_level.txt
doc/Makefile
doc/index.txt
doc/source/api.rst
doc/source/conf.py
doc/source/index.rst
doc/source/manual.rst
dreamweavertemplate/__init__.py
dreamweavertemplate/command.py
dreamweavertemplate/decorator.py
dreamweavertemplate/service.py
example/README.txt
test/README.txt
test/doc.py