Metadata-Version: 1.0
Name: DreamweaverTemplate
Version: 0.2.2
Summary: Parse Dreamweaver templates (.dwt files), includes a pipe to dynamically render templates.
Home-page: http://jimmyg.org/work/code/dreamweavertemplate/index.html
Author: James Gardner
Author-email: UNKNOWN
License: GNU AGPLv3
Platform: UNKNOWN
Classifier: Development Status :: 3 - Alpha
Classifier: License :: OSI Approved :: GNU Affero General Public License v3
Classifier: Programming Language :: Python :: 2
Classifier: Topic :: Software Development :: Libraries :: Python Modules
Classifier: Topic :: Internet :: WWW/HTTP :: Dynamic Content
